Metadata-Version: 2.0
Name: zeep-adv
Version: 1.4.4
Summary: A modern/fast Python SOAP client based on lxml / requests + Corentin Remaud silly edit
Home-page: http://docs.python-zeep.org
Author: Michael van Tellingen, some edit by Corentin Remaud
Author-email: remaudcorentin.dev@gmail.com
License: MIT
Platform: UNKNOWN
Classifier: Development Status :: 5 - Production/Stable
Classifier: License :: OSI Approved :: MIT License
Classifier: Programming Language :: Python :: 2
Classifier: Programming Language :: Python :: 2.7
Classifier: Programming Language :: Python :: 3
Classifier: Programming Language :: Python :: 3.3
Classifier: Programming Language :: Python :: 3.4
Classifier: Programming Language :: Python :: 3.5
Classifier: Programming Language :: Python :: 3.6
Classifier: Programming Language :: Python :: Implementation :: CPython
Classifier: Programming Language :: Python :: Implementation :: PyPy
Requires-Dist: appdirs (>=1.4.0)
Requires-Dist: cached-property (>=1.3.0)
Requires-Dist: defusedxml (>=0.4.1)
Requires-Dist: isodate (>=0.5.4)
Requires-Dist: lxml (>=3.0.0)
Requires-Dist: pytz
Requires-Dist: requests (>=2.7.0)
Requires-Dist: requests-toolbelt (>=0.7.1)
Requires-Dist: six (>=1.9.0)
Provides-Extra: async
Requires-Dist: aiohttp (>=1.0); extra == 'async'
Requires-Dist: aioresponses (>=0.1.3); extra == 'async'
Provides-Extra: docs
Requires-Dist: sphinx (>=1.4.0); extra == 'docs'
Provides-Extra: test
Requires-Dist: flake8 (==3.2.1); extra == 'test'
Requires-Dist: flake8-blind-except (==0.1.1); extra == 'test'
Requires-Dist: flake8-debugger (==1.4.0); extra == 'test'
Requires-Dist: freezegun (==0.3.8); extra == 'test'
Requires-Dist: isort (==4.2.5); extra == 'test'
Requires-Dist: mock (==2.0.0); extra == 'test'
Requires-Dist: pretend (==1.0.8); extra == 'test'
Requires-Dist: pytest (==3.0.6); extra == 'test'
Requires-Dist: pytest-cov (==2.4.0); extra == 'test'
Requires-Dist: requests-mock (>=0.7.0); extra == 'test'
Provides-Extra: xmlsec
Requires-Dist: xmlsec (>=0.6.1); extra == 'xmlsec'
